{"stats":{"minecraft:used":{"minecraft:netherite_sword":13,"rlovelyr:vanilla_spawn":3},"minecraft:custom":{"minecraft:jump":3,"minecraft:time_since_rest":971,"minecraft:damage_dealt":800,"minecraft:leave_game":1,"minecraft:play_time":1877,"minecraft:deaths":1,"minecraft:time_since_death":926,"minecraft:walk_one_cm":5208,"minecraft:sneak_time":4,"minecraft:total_world_time":1913,"minecraft:mob_kills":4,"minecraft:fly_one_cm":5873},"minecraft:picked_up":{"rlovelyr:vanilla_spawn":1},"minecraft:killed":{"rlovelyr:vanilla":4}},"DataVersion":3218}