{"stats":{"minecraft:used":{"minecraft:netherite_sword":1,"rlovelyr:vanilla_spawn":2},"minecraft:custom":{"minecraft:jump":8,"minecraft:time_since_rest":2812,"minecraft:damage_dealt":80,"minecraft:crouch_one_cm":51,"minecraft:leave_game":2,"minecraft:play_time":2812,"minecraft:sprint_one_cm":185,"minecraft:time_since_death":2812,"minecraft:walk_one_cm":15275,"minecraft:sneak_time":37,"minecraft:total_world_time":2947,"minecraft:mob_kills":1,"minecraft:fly_one_cm":10254},"minecraft:killed":{"rlovelyr:vanilla":1}},"DataVersion":3218}